thimble/__init__.py
thimble/_version.py
thimble/wrapper.py
thimble/test/__init__.py
thimble/test/test_util.py
thimble/test/test_version.py
thimble/test/test_wrapper.py
thimble/test/util.py
thimble-0.2.0.dist-info/DESCRIPTION.rst
thimble-0.2.0.dist-info/METADATA
thimble-0.2.0.dist-info/RECORD
thimble-0.2.0.dist-info/WHEEL
thimble-0.2.0.dist-info/metadata.json
thimble-0.2.0.dist-info/top_level.txt
thimble-0.2.0.dist-info/zip-safe
