Metadata-Version: 2.0
Name: thimble
Version: 0.2.0
Summary: A Twisted thread-pool based wrapper for blocking APIs.
Home-page: https://github.com/lvh/thimble
Author: lvh
Author-email: _@lvh.io
License: Apache 2.0
Keywords: twisted threads thread compat compatibility async asynchronous
Platform: UNKNOWN
Classifier: Development Status :: 3 - Alpha
Classifier: Framework :: Twisted
Classifier: Intended Audience :: Developers
Classifier: License :: OSI Approved :: Apache Software License
Classifier: Programming Language :: Python :: 2 :: Only
Classifier: Programming Language :: Python :: 2.7
Requires-Dist: Twisted (==14.0)
Requires-Dist: zope.interface (==4.1.1)
